IgProfileClient/__init__.py
IgProfileClient/client.py
IgProfileClient/version.py
poon_ig_profile_client-0.0.1.dist-info/licenses/LICENSE.md
tests/__init__.py
tests/test_get_common_profile.py
poon_ig_profile_client-0.0.1.dist-info/METADATA
poon_ig_profile_client-0.0.1.dist-info/WHEEL
poon_ig_profile_client-0.0.1.dist-info/top_level.txt
poon_ig_profile_client-0.0.1.dist-info/RECORD
